Workbook

Sheet Dashboard
A1: UK COOKIE CONSENT — PROJECT FINANCES
A2: SaaS Subscription Revenue & Expense Tracker — 2026
A4: REVENUE & PROFIT | E4: MONTHLY P&L SUMMARY
A5: Monthly Recurring Revenue (MRR) | B5: =IFERROR(SUMIF('MRR Tracker'!B2:B500,"Active",'MRR Tracker'!D2:D500),0) -> 0 | E5: Month | F5: Revenue | G5: Expenses | H5: Net Profit
A6: Annual Recurring Revenue (ARR) | B6: =B5*12 -> 0 | E6: Jan | F6: =SUMPRODUCT((MONTH('Revenue Log'!A2:A500)=1)*(YEAR('Revenue Log'!A2:A500)=2026)*('Revenue Log'!E2:E500)) -> 0 | G6: =SUMPRODUCT((MONTH(Expenses!A2:A500)=1)*(YEAR(Expenses!A2:A500)=2026)*(Expenses!E2:E500)) -> 0 | H6: =F6-G6 -> 0
A7: Total Revenue (YTD) | B7: =SUMIF('Revenue Log'!A2:A500,">="&DATE(2026,1,1),'Revenue Log'!E2:E500) -> 0 | E7: Feb | F7: =SUMPRODUCT((MONTH('Revenue Log'!A2:A500)=2)*(YEAR('Revenue Log'!A2:A500)=2026)*('Revenue Log'!E2:E500)) -> 0 | G7: =SUMPRODUCT((MONTH(Expenses!A2:A500)=2)*(YEAR(Expenses!A2:A500)=2026)*(Expenses!E2:E500)) -> 0 | H7: =F7-G7 -> 0
A8: Total Expenses (YTD) | B8: =SUMPRODUCT((Expenses!E2:E500)*(Expenses!A2:A500<>"")) -> 0 | E8: Mar | F8: =SUMPRODUCT((MONTH('Revenue Log'!A2:A500)=3)*(YEAR('Revenue Log'!A2:A500)=2026)*('Revenue Log'!E2:E500)) -> 0 | G8: =SUMPRODUCT((MONTH(Expenses!A2:A500)=3)*(YEAR(Expenses!A2:A500)=2026)*(Expenses!E2:E500)) -> 0 | H8: =F8-G8 -> 0
A9: Net Profit (YTD) | B9: =B7-B8 -> 0 | E9: Apr | F9: =SUMPRODUCT((MONTH('Revenue Log'!A2:A500)=4)*(YEAR('Revenue Log'!A2:A500)=2026)*('Revenue Log'!E2:E500)) -> 0 | G9: =SUMPRODUCT((MONTH(Expenses!A2:A500)=4)*(YEAR(Expenses!A2:A500)=2026)*(Expenses!E2:E500)) -> 0 | H9: =F9-G9 -> 0
A10: Profit Margin | B10: =IF(B7=0,0,B9/B7) -> 0 | E10: May | F10: =SUMPRODUCT((MONTH('Revenue Log'!A2:A500)=5)*(YEAR('Revenue Log'!A2:A500)=2026)*('Revenue Log'!E2:E500)) -> 0 | G10: =SUMPRODUCT((MONTH(Expenses!A2:A500)=5)*(YEAR(Expenses!A2:A500)=2026)*(Expenses!E2:E500)) -> 0 | H10: =F10-G10 -> 0
E11: Jun | F11: =SUMPRODUCT((MONTH('Revenue Log'!A2:A500)=6)*(YEAR('Revenue Log'!A2:A500)=2026)*('Revenue Log'!E2:E500)) -> 0 | G11: =SUMPRODUCT((MONTH(Expenses!A2:A500)=6)*(YEAR(Expenses!A2:A500)=2026)*(Expenses!E2:E500)) -> 0 | H11: =F11-G11 -> 0
A12: SUBSCRIBERS | E12: Jul | F12: =SUMPRODUCT((MONTH('Revenue Log'!A2:A500)=7)*(YEAR('Revenue Log'!A2:A500)=2026)*('Revenue Log'!E2:E500)) -> 0 | G12: =SUMPRODUCT((MONTH(Expenses!A2:A500)=7)*(YEAR(Expenses!A2:A500)=2026)*(Expenses!E2:E500)) -> 0 | H12: =F12-G12 -> 0
A13: Total Active Subscribers | B13: =COUNTIF('MRR Tracker'!B2:B500,"Active") -> 0 | E13: Aug | F13: =SUMPRODUCT((MONTH('Revenue Log'!A2:A500)=8)*(YEAR('Revenue Log'!A2:A500)=2026)*('Revenue Log'!E2:E500)) -> 0 | G13: =SUMPRODUCT((MONTH(Expenses!A2:A500)=8)*(YEAR(Expenses!A2:A500)=2026)*(Expenses!E2:E500)) -> 0 | H13: =F13-G13 -> 0
A14: Free Plan Users | B14: =COUNTIF('MRR Tracker'!C2:C500,"Free") -> 0 | E14: Sep | F14: =SUMPRODUCT((MONTH('Revenue Log'!A2:A500)=9)*(YEAR('Revenue Log'!A2:A500)=2026)*('Revenue Log'!E2:E500)) -> 0 | G14: =SUMPRODUCT((MONTH(Expenses!A2:A500)=9)*(YEAR(Expenses!A2:A500)=2026)*(Expenses!E2:E500)) -> 0 | H14: =F14-G14 -> 0
A15: Paid Subscribers | B15: =COUNTIF('MRR Tracker'!C2:C500,"Paid") -> 0 | E15: Oct | F15: =SUMPRODUCT((MONTH('Revenue Log'!A2:A500)=10)*(YEAR('Revenue Log'!A2:A500)=2026)*('Revenue Log'!E2:E500)) -> 0 | G15: =SUMPRODUCT((MONTH(Expenses!A2:A500)=10)*(YEAR(Expenses!A2:A500)=2026)*(Expenses!E2:E500)) -> 0 | H15: =F15-G15 -> 0
A16: Churned (YTD) | B16: =COUNTIF('MRR Tracker'!B2:B500,"Churned") -> 0 | E16: Nov | F16: =SUMPRODUCT((MONTH('Revenue Log'!A2:A500)=11)*(YEAR('Revenue Log'!A2:A500)=2026)*('Revenue Log'!E2:E500)) -> 0 | G16: =SUMPRODUCT((MONTH(Expenses!A2:A500)=11)*(YEAR(Expenses!A2:A500)=2026)*(Expenses!E2:E500)) -> 0 | H16: =F16-G16 -> 0
A17: Churn Rate | B17: =IF(B13+B16=0,0,B16/(B13+B16)) -> 0 | E17: Dec | F17: =SUMPRODUCT((MONTH('Revenue Log'!A2:A500)=12)*(YEAR('Revenue Log'!A2:A500)=2026)*('Revenue Log'!E2:E500)) -> 0 | G17: =SUMPRODUCT((MONTH(Expenses!A2:A500)=12)*(YEAR(Expenses!A2:A500)=2026)*(Expenses!E2:E500)) -> 0 | H17: =F17-G17 -> 0
A18: Avg Revenue Per User (ARPU) | B18: =IF(B15=0,0,B5/B15) -> 0 | E18: TOTAL | F18: =SUM(F6:F17) -> 0 | G18: =SUM(G6:G17) -> 0 | H18: =SUM(H6:H17) -> 0
A20: EXPENSE BREAKDOWN
A21: Category | B21: YTD Amount | C21: % of Expenses
A22: Hosting/Vercel | B22: =SUMIF(Expenses!C2:C500,A22,Expenses!E2:E500) -> 20 | C22: =IF(B8=0,0,B22/B8) -> 0
A23: Supabase/DB | B23: =SUMIF(Expenses!C2:C500,A23,Expenses!E2:E500) -> 25 | C23: =IF(B8=0,0,B23/B8) -> 0
A24: Domain & SSL | B24: =SUMIF(Expenses!C2:C500,A24,Expenses!E2:E500) -> 0 | C24: =IF(B8=0,0,B24/B8) -> 0
A25: Stripe Fees | B25: =SUMIF(Expenses!C2:C500,A25,Expenses!E2:E500) -> 0 | C25: =IF(B8=0,0,B25/B8) -> 0
A26: Software/Tools | B26: =SUMIF(Expenses!C2:C500,A26,Expenses!E2:E500) -> 0 | C26: =IF(B8=0,0,B26/B8) -> 0
A27: Marketing | B27: =SUMIF(Expenses!C2:C500,A27,Expenses!E2:E500) -> 0 | C27: =IF(B8=0,0,B27/B8) -> 0
A28: Contractors | B28: =SUMIF(Expenses!C2:C500,A28,Expenses!E2:E500) -> 0 | C28: =IF(B8=0,0,B28/B8) -> 0
A29: Other | B29: =SUMIF(Expenses!C2:C500,A29,Expenses!E2:E500) -> 0 | C29: =IF(B8=0,0,B29/B8) -> 0

Sheet MRR Tracker
A1: Subscriber ID | B1: Status | C1: Plan Type | D1: MRR ($) | E1: Start Date | F1: Churn Date | G1: Stripe Customer ID | H1: Email | I1: Notes

Sheet Revenue Log
A1: Date | B1: Subscriber ID | C1: Type | D1: Description | E1: Amount | F1: Stripe Fee | G1: Net Amount | H1: Payment Status | I1: Stripe Charge ID | J1: Notes
A2: 46096.614 | B2: cus_U9Z2a3mtbhrVBh | C2: One-Time | E2: 99 | F2: 0 | G2: 99 | H2: Paid | I2: ch_3TBFu6ANLJbikAiY12yL7hE1

Sheet Expenses
A1: Date | B1: Vendor | C1: Category | D1: Description | E1: Amount | F1: Billing Cycle | G1: Payment Method | H1: Receipt? | I1: Tax Deductible? | J1: Notes
A2: 46082 | B2: Vercel | C2: Hosting/Vercel | D2: Vercel Hobby (free tier) | E2: 0 | F2: Monthly | G2: N/A | H2: N/A | I2: N/A | J2: Free tier
A3: 46082 | B3: Supabase | C3: Supabase/DB | D3: Supabase Free tier | E3: 0 | F3: Monthly | G3: N/A | H3: N/A | I3: N/A | J3: Free tier
A4: 46082 | B4: Resend | C4: Software/Tools | D4: Resend email (free tier) | E4: 0 | F4: Monthly | G4: N/A | H4: N/A | I4: N/A | J4: 100 emails/day
A5: 46082 | B5: PostHog | C5: Software/Tools | D5: PostHog analytics (free tier) | E5: 0 | F5: Monthly | G5: N/A | H5: N/A | I5: N/A | J5: 1M events/mo
A6: 46082 | B6: Stripe | C6: Software/Tools | D6: Stripe (no monthly fee) | E6: 0 | F6: Monthly | G6: N/A | H6: N/A | I6: N/A | J6: Fees deducted per-txn in Revenue Log
A7: 46082 | B7: Next.js | C7: Software/Tools | D7: Next.js framework (open source) | E7: 0 | F7: Monthly | G7: N/A | H7: N/A | I7: N/A | J7: Free / open source

Sheet Tax & Profit
A1: UK COOKIE CONSENT — TAX & PROFIT SUMMARY 2026
A3: QUARTERLY BREAKDOWN
B4: Q1 (Jan–Mar) | C4: Q2 (Apr–Jun) | D4: Q3 (Jul–Sep) | E4: Q4 (Oct–Dec)
A5: Gross Revenue | B5: =SUMPRODUCT((MONTH('Revenue Log'!A2:A500)>=1)*(MONTH('Revenue Log'!A2:A500)<=3)*(YEAR('Revenue Log'!A2:A500)=2026)*('Revenue Log'!E2:E500)) -> 0 | C5: =SUMPRODUCT((MONTH('Revenue Log'!A2:A500)>=4)*(MONTH('Revenue Log'!A2:A500)<=6)*(YEAR('Revenue Log'!A2:A500)=2026)*('Revenue Log'!E2:E500)) -> 0 | D5: =SUMPRODUCT((MONTH('Revenue Log'!A2:A500)>=7)*(MONTH('Revenue Log'!A2:A500)<=9)*(YEAR('Revenue Log'!A2:A500)=2026)*('Revenue Log'!E2:E500)) -> 0 | E5: =SUMPRODUCT((MONTH('Revenue Log'!A2:A500)>=10)*(MONTH('Revenue Log'!A2:A500)<=12)*(YEAR('Revenue Log'!A2:A500)=2026)*('Revenue Log'!E2:E500)) -> 0
A6: Stripe Fees | B6: =SUMPRODUCT((MONTH('Revenue Log'!A2:A500)>=1)*(MONTH('Revenue Log'!A2:A500)<=3)*(YEAR('Revenue Log'!A2:A500)=2026)*('Revenue Log'!F2:F500)) -> 0 | C6: =SUMPRODUCT((MONTH('Revenue Log'!A2:A500)>=4)*(MONTH('Revenue Log'!A2:A500)<=6)*(YEAR('Revenue Log'!A2:A500)=2026)*('Revenue Log'!F2:F500)) -> 0 | D6: =SUMPRODUCT((MONTH('Revenue Log'!A2:A500)>=7)*(MONTH('Revenue Log'!A2:A500)<=9)*(YEAR('Revenue Log'!A2:A500)=2026)*('Revenue Log'!F2:F500)) -> 0 | E6: =SUMPRODUCT((MONTH('Revenue Log'!A2:A500)>=10)*(MONTH('Revenue Log'!A2:A500)<=12)*(YEAR('Revenue Log'!A2:A500)=2026)*('Revenue Log'!F2:F500)) -> 0
A7: Net Revenue | B7: =B5-B6 -> 0 | C7: =C5-C6 -> 0 | D7: =D5-D6 -> 0 | E7: =E5-E6 -> 0
A8: Operating Expenses | B8: =SUMPRODUCT((MONTH(Expenses!A2:A500)>=1)*(MONTH(Expenses!A2:A500)<=3)*(YEAR(Expenses!A2:A500)=2026)*(Expenses!E2:E500)) -> 0 | C8: =SUMPRODUCT((MONTH(Expenses!A2:A500)>=4)*(MONTH(Expenses!A2:A500)<=6)*(YEAR(Expenses!A2:A500)=2026)*(Expenses!E2:E500)) -> 0 | D8: =SUMPRODUCT((MONTH(Expenses!A2:A500)>=7)*(MONTH(Expenses!A2:A500)<=9)*(YEAR(Expenses!A2:A500)=2026)*(Expenses!E2:E500)) -> 0 | E8: =SUMPRODUCT((MONTH(Expenses!A2:A500)>=10)*(MONTH(Expenses!A2:A500)<=12)*(YEAR(Expenses!A2:A500)=2026)*(Expenses!E2:E500)) -> 0
A9: Net Profit | B9: =B7-B8 -> 0 | C9: =C7-C8 -> 0 | D9: =D7-D8 -> 0 | E9: =E7-E8 -> 0
A10: Est. Tax (25%) | B10: =MAX(B9*0.25,0) -> 0 | C10: =MAX(C9*0.25,0) -> 0 | D10: =MAX(D9*0.25,0) -> 0 | E10: =MAX(E9*0.25,0) -> 0
A12: ANNUAL TOTALS
A13: Total Gross Revenue | B13: =SUM(B5:E5) -> 0
A14: Total Stripe Fees | B14: =SUM(B6:E6) -> 0
A15: Net Revenue | B15: =SUM(B7:E7) -> 0
A16: Total Expenses | B16: =SUM(B8:E8) -> 0
A17: Net Profit | B17: =SUM(B9:E9) -> 0
A18: Est. Annual Tax (25%) | B18: =MAX(B17*0.25,0) -> 0
A19: Take-Home | B19: =B17-B18 -> 0
A21: SAAS DEDUCTIONS CHECKLIST
A22: Deduction | B22: Amount | C22: Tracked? | D22: Notes
A23: Vercel / Hosting Costs
A24: Supabase / Database Costs
A25: Domain & SSL Certificates
A26: Stripe & Payment Fees
A27: Software Subscriptions (dev tools, AI, etc.)
A28: Marketing & Ads
A29: Contractor / Developer Payments
A30: Home Office (Simplified: $5/sq ft)
A31: Internet (Business %)
A32: Professional Services (Legal, Accounting)
A33: Education / Courses
A34: Equipment (Laptop, Monitors, etc.)
A35: TOTAL DEDUCTIONS | B35: =SUM(B23:B34) -> 0
